flake8_isort.py
flake9_isort-4.0.2.dist-info/LICENSE
flake9_isort-4.0.2.dist-info/LICENSE.rst
flake9_isort-4.0.2.dist-info/METADATA
flake9_isort-4.0.2.dist-info/WHEEL
flake9_isort-4.0.2.dist-info/entry_points.txt
flake9_isort-4.0.2.dist-info/top_level.txt
flake9_isort-4.0.2.dist-info/RECORD
